MANIFEST.in
README.rst
setup.py
Fanery.egg-info/PKG-INFO
Fanery.egg-info/SOURCES.txt
Fanery.egg-info/dependency_links.txt
Fanery.egg-info/requires.txt
Fanery.egg-info/top_level.txt
docs/backend-web-farm.rst
docs/fanery.rst
docs/hardened-system.rst
docs/index.rst
docs/intro.rst
docs/security-protocol.rst
docs/storage.rst
docs/tutorial.rst
docs/window-system.rst
docs/working-with-fanery.rst
fanery/__init__.py
fanery/_auth.py
fanery/_autoreload.py
fanery/_client.py
fanery/_config.py
fanery/_crypto.py
fanery/_dbm.py
fanery/_dsdb.py
fanery/_esdb.py
fanery/_exc.py
fanery/_hddb.py
fanery/_mddb.py
fanery/_profile.py
fanery/_random.py
fanery/_rtdb.py
fanery/_server.py
fanery/_service.py
fanery/_state.py
fanery/_store.py
fanery/_term.py
fanery/_version.py
fanery/_wsgi.py
fanery/jfanery/base64.js
fanery/jfanery/example.html
fanery/jfanery/jfanery.js
fanery/jfanery/jquery.js
fanery/jfanery/json2.js
fanery/jfanery/nacl_factory.js
fanery/jfanery/scrypt.js
fanery/tests/__init__.py
fanery/tests/test_service.py
fanery/tests/test_term.py